<?xml version="1.0" encoding="iso-8859-1" ?>

<CustomData>
  <CustomGroups>
    <CustomGroup>
      <name>Direct_Debit_Mandate</name>
      <title>Direct Debit Mandate</title>
      <extends>Contact</extends>
      <style>Tab</style>
      <collapse_display>0</collapse_display>
      <help_pre></help_pre>
      <help_post></help_post>
      <weight>1</weight>
      <is_active>1</is_active>
      <table_name>civicrm_value_bank_details</table_name>
      <is_multiple>1</is_multiple>
      <collapse_adv_display>1</collapse_adv_display>
      <created_date>2010-12-14 09:28:04</created_date>
    </CustomGroup>
    <CustomGroup>
      <name>Direct_Debit_Files</name>
      <title>Direct Debit Files</title>
      <extends>Contact</extends>
      <style>Tab</style>
      <collapse_display>0</collapse_display>
      <help_pre></help_pre>
      <help_post></help_post>
      <weight>1</weight>
      <is_active>1</is_active>
      <table_name>civicrm_value_direct_debit_files</table_name>
      <is_multiple>1</is_multiple>
      <collapse_adv_display>1</collapse_adv_display>
      <created_date>2010-12-14 09:28:04</created_date>
    </CustomGroup>
    <CustomGroup>
      <name>Direct_Debit</name>
      <title>Direct Debit Details</title>
      <extends>Contribution</extends>
      <style>Inline</style>
      <collapse_display>0</collapse_display>
      <help_pre>Stores the values that are related to Direct Debit</help_pre>
      <help_post></help_post>
      <weight>3</weight>
      <is_active>1</is_active>
      <table_name>civicrm_value_direct_debit_details</table_name>
      <is_multiple>0</is_multiple>
      <collapse_adv_display>0</collapse_adv_display>
      <created_date>2010-12-15 12:54:48</created_date>
    </CustomGroup>
    <CustomGroup>
      <name>Activity_Bank_Relationship</name>
      <title>Activity Bank Relationship</title>
      <extends>Activity</extends>
      <style>Inline</style>
      <collapse_display>0</collapse_display>
      <help_pre></help_pre>
      <help_post></help_post>
      <weight>1</weight>
      <is_active>1</is_active>
      <table_name>civicrm_value_activity_bank_relationship</table_name>
      <is_multiple>0</is_multiple>
      <collapse_adv_display>1</collapse_adv_display>
      <created_date>2010-12-14 09:28:04</created_date>
    </CustomGroup>
    <CustomGroup>
      <name>Payment_Method</name>
      <title>Payment Method</title>
      <extends>Membership</extends>
      <style>Inline</style>
      <collapse_display>0</collapse_display>
      <help_pre></help_pre>
      <help_post></help_post>
      <weight>3</weight>
      <is_active>1</is_active>
      <table_name>civicrm_value_payment_method</table_name>
      <is_multiple>0</is_multiple>
      <collapse_adv_display>0</collapse_adv_display>
      <created_date>2010-12-15 12:54:48</created_date>
    </CustomGroup>
  </CustomGroups>
  <CustomFields>
    <CustomField>
      <name>Direct_Debit</name>
      <label>Direct Debit</label>
      <data_type>Boolean</data_type>
      <html_type>Radio</html_type>
      <default_value>0</default_value>
      <is_required>0</is_required>
      <is_searchable>0</is_searchable>
      <is_search_range>0</is_search_range>
      <weight>1</weight>
      <is_active>1</is_active>
      <is_view>0</is_view>
      <text_length>255</text_length>
      <note_columns>60</note_columns>
      <note_rows>4</note_rows>
      <column_name>direct_debit</column_name>
      <custom_group_name>Payment_Method</custom_group_name>
    </CustomField> 
    <CustomField>
      <name>Bank Id</name>
      <label>Mandate Id</label>
      <data_type>String</data_type>
      <html_type>Text</html_type>
      <is_required>0</is_required>
      <is_searchable>0</is_searchable>
      <is_search_range>0</is_search_range>
      <weight>1</weight>
      <is_active>1</is_active>
      <is_view>0</is_view>
      <text_length>255</text_length>
      <note_columns>150</note_columns>
      <note_rows>4</note_rows>
      <column_name>bank_id</column_name>
      <custom_group_name>Activity_Bank_Relationship</custom_group_name>
    </CustomField>
    <CustomField>
      <name>File Type</name>
      <label>File Type</label>
      <data_type>String</data_type>
      <html_type>Text</html_type>
      <is_required>0</is_required>
      <is_searchable>0</is_searchable>
      <is_search_range>0</is_search_range>
      <weight>1</weight>
      <is_active>1</is_active>
      <is_view>1</is_view>
      <text_length>255</text_length>
      <note_columns>150</note_columns>
      <note_rows>4</note_rows>
      <column_name>direct_debit_file_type</column_name>
      <custom_group_name>Direct_Debit_Files</custom_group_name>
    </CustomField>
    <CustomField>
      <name>Related File</name>
      <label>Related File</label>
      <data_type>File</data_type>
      <html_type>File</html_type>
      <is_required>0</is_required>
      <is_searchable>0</is_searchable>
      <is_search_range>0</is_search_range>
      <weight>2</weight>
      <is_active>1</is_active>
      <is_view>1</is_view>
      <text_length>255</text_length>
      <note_columns>60</note_columns>
      <note_rows>4</note_rows>
      <column_name>direct_debit_related_file</column_name>
      <custom_group_name>Direct_Debit_Files</custom_group_name>
    </CustomField>
    <CustomField>
      <name>Associated_Mandate_Id</name>
      <label>Associated Mandate Id</label>
      <data_type>String</data_type>
      <html_type>Text</html_type>
      <is_required>0</is_required>
      <is_searchable>0</is_searchable>
      <is_search_range>0</is_search_range>
      <weight>1</weight>
      <is_active>1</is_active>
      <is_view>1</is_view>
      <text_length>255</text_length>
      <note_columns>150</note_columns>
      <note_rows>4</note_rows>
      <column_name>mandate_id</column_name>
      <custom_group_name>Direct_Debit</custom_group_name>
    </CustomField>
    <CustomField>
      <name>Activity_Id</name>
      <label>Activity Id</label>
      <data_type>String</data_type>
      <html_type>Text</html_type>
      <is_required>0</is_required>
      <is_searchable>0</is_searchable>
      <is_search_range>0</is_search_range>
      <weight>2</weight>
      <is_active>1</is_active>
      <is_view>1</is_view>
      <text_length>255</text_length>
      <note_columns>150</note_columns>
      <note_rows>4</note_rows>
      <column_name>activity_id</column_name>
      <custom_group_name>Direct_Debit</custom_group_name>
    </CustomField>
    <CustomField>
      <name>Added_to_Direct_Debit_batch</name>
      <label>Added to Direct Debit batch?</label>
      <data_type>Boolean</data_type>
      <html_type>Radio</html_type>
      <default_value>0</default_value>
      <is_required>0</is_required>
      <is_searchable>0</is_searchable>
      <is_search_range>0</is_search_range>
      <weight>3</weight>
      <is_active>1</is_active>
      <is_view>1</is_view>
      <text_length>255</text_length>
      <note_columns>60</note_columns>
      <note_rows>4</note_rows>
      <column_name>added_to_direct_debit</column_name>
      <custom_group_name>Direct_Debit</custom_group_name>
    </CustomField>
    <CustomField>
      <name>Process_as_Rejection</name>
      <label>Process as Rejection?</label>
      <data_type>Boolean</data_type>
      <html_type>Radio</html_type>
      <default_value>0</default_value>
      <is_required>0</is_required>
      <is_searchable>0</is_searchable>
      <is_search_range>0</is_search_range>
      <weight>4</weight>
      <is_active>1</is_active>
      <is_view>0</is_view>
      <text_length>255</text_length>
      <column_name>process_as_rejection</column_name>
      <help_pre>Important: Please select Yes only if this contribution is rejected already and you want to add this contribution to the next immediate batch.</help_pre>
      <custom_group_name>Direct_Debit</custom_group_name>
    </CustomField> 
    <CustomField>
      <name>Mandate_Primary_Key</name>
      <label>Mandate Id</label>
      <data_type>String</data_type>
      <html_type>Text</html_type>
      <is_required>0</is_required>
      <is_searchable>0</is_searchable>
      <is_search_range>0</is_search_range>
      <weight>1</weight>
      <is_active>1</is_active>
      <is_view>1</is_view>
      <text_length>255</text_length>
      <note_columns>150</note_columns>
      <note_rows>4</note_rows>
      <column_name>mandate_id</column_name>
      <custom_group_name>Direct_Debit_Mandate</custom_group_name>
    </CustomField>
    <CustomField>
      <name>Bank_Name</name>
      <label>Bank/Building Society</label>
      <data_type>String</data_type>
      <html_type>Text</html_type>
      <is_required>0</is_required>
      <is_searchable>0</is_searchable>
      <is_search_range>0</is_search_range>
      <weight>2</weight>
      <is_active>1</is_active>
      <is_view>0</is_view>
      <text_length>255</text_length>
      <note_columns>150</note_columns>
      <note_rows>4</note_rows>
      <column_name>bank_name</column_name>
      <custom_group_name>Direct_Debit_Mandate</custom_group_name>
    </CustomField>
    <CustomField>
      <name>Bank_Address</name>
      <label>Bank/Building Society number and street</label>
      <data_type>String</data_type>
      <html_type>Text</html_type>
      <is_required>0</is_required>
      <is_searchable>0</is_searchable>
      <is_search_range>0</is_search_range>
      <weight>3</weight>
      <is_active>1</is_active>
      <is_view>0</is_view>
      <text_length>255</text_length>
      <note_columns>150</note_columns>
      <note_rows>4</note_rows>
      <column_name>bank_address</column_name>
      <custom_group_name>Direct_Debit_Mandate</custom_group_name>
    </CustomField>
    <CustomField>
      <name>Bank_City</name>
      <label>Town/City</label>
      <data_type>String</data_type>
      <html_type>Text</html_type>
      <is_required>0</is_required>
      <is_searchable>0</is_searchable>
      <is_search_range>0</is_search_range>
      <weight>4</weight>
      <is_active>1</is_active>
      <is_view>0</is_view>
      <text_length>255</text_length>
      <note_columns>150</note_columns>
      <note_rows>4</note_rows>
      <column_name>bank_city</column_name>
      <custom_group_name>Direct_Debit_Mandate</custom_group_name>
    </CustomField>
     <CustomField>
      <name>Bank_County</name>
      <label>County</label>
      <data_type>String</data_type>
      <html_type>Text</html_type>
      <is_required>0</is_required>
      <is_searchable>0</is_searchable>
      <is_search_range>0</is_search_range>
      <weight>5</weight>
      <is_active>1</is_active>
      <is_view>0</is_view>
      <text_length>255</text_length>
      <note_columns>150</note_columns>
      <note_rows>4</note_rows>
      <column_name>bank_county</column_name>
      <custom_group_name>Direct_Debit_Mandate</custom_group_name>
    </CustomField>
    <CustomField>
      <name>Bank_PostCode</name>
      <label>Postcode</label>
      <data_type>String</data_type>
      <html_type>Text</html_type>
      <is_required>0</is_required>
      <is_searchable>0</is_searchable>
      <is_search_range>0</is_search_range>
      <weight>6</weight>
      <is_active>1</is_active>
      <is_view>0</is_view>
      <text_length>255</text_length>
      <note_columns>150</note_columns>
      <note_rows>4</note_rows>
      <column_name>bank_postcode</column_name>
      <custom_group_name>Direct_Debit_Mandate</custom_group_name>
    </CustomField>
    <CustomField>
      <name>Account_Number</name>
      <label>Account Number</label>
      <data_type>String</data_type>
      <html_type>Text</html_type>
      <is_required>0</is_required>
      <is_searchable>0</is_searchable>
      <is_search_range>0</is_search_range>
      <weight>7</weight>
      <is_active>1</is_active>
      <is_view>0</is_view>
      <text_length>255</text_length>
      <note_columns>60</note_columns>
      <note_rows>4</note_rows>
      <column_name>account_number</column_name>
      <custom_group_name>Direct_Debit_Mandate</custom_group_name>
    </CustomField>
    <CustomField>
      <name>Bank_Sort_Number</name>
      <label>Bank Sort Number</label>
      <data_type>String</data_type>
      <html_type>Text</html_type>
      <is_required>0</is_required>
      <is_searchable>0</is_searchable>
      <is_search_range>0</is_search_range>
      <weight>8</weight>
      <is_active>1</is_active>
      <is_view>0</is_view>
      <text_length>255</text_length>
      <note_columns>60</note_columns>
      <note_rows>4</note_rows>
      <column_name>sort_code</column_name>
      <custom_group_name>Direct_Debit_Mandate</custom_group_name>
    </CustomField>
    <CustomField>
      <name>Account_Name</name>
      <label>Account Holder Name</label>
      <data_type>String</data_type>
      <html_type>Text</html_type>
      <is_required>0</is_required>
      <is_searchable>0</is_searchable>
      <is_search_range>0</is_search_range>
      <weight>9</weight>
      <is_active>1</is_active>
      <is_view>0</is_view>
      <text_length>255</text_length>
      <note_columns>150</note_columns>
      <note_rows>4</note_rows>
      <column_name>account_name</column_name>
      <custom_group_name>Direct_Debit_Mandate</custom_group_name>
    </CustomField>    
    <CustomField>
      <name>BACS_Ref_Number</name>
      <label>BACS Ref Number</label>
      <data_type>String</data_type>
      <html_type>Text</html_type>
      <is_required>0</is_required>
      <is_searchable>0</is_searchable>
      <is_search_range>0</is_search_range>
      <weight>10</weight>
      <is_active>1</is_active>
      <is_view>0</is_view>
      <text_length>255</text_length>
      <note_columns>60</note_columns>
      <note_rows>4</note_rows>
      <column_name>bacs_ref_number</column_name>
      <custom_group_name>Direct_Debit_Mandate</custom_group_name>
    </CustomField>
    <CustomField>
      <name>Start_Date</name>
      <label>Start Date</label>
      <data_type>Date</data_type>
      <html_type>Select Date</html_type>
      <is_required>0</is_required>
      <is_searchable>0</is_searchable>
      <is_search_range>0</is_search_range>
      <weight>11</weight>
      <is_active>1</is_active>
      <is_view>0</is_view>
      <text_length>255</text_length>
      <date_format>mm/dd/yy</date_format>
      <note_columns>60</note_columns>
      <note_rows>4</note_rows>
      <column_name>start_date</column_name>
      <custom_group_name>Direct_Debit_Mandate</custom_group_name>
    </CustomField>
    <CustomField>
      <name>Cease_Date</name>
      <label>Cease Date</label>
      <data_type>Date</data_type>
      <html_type>Select Date</html_type>
      <is_required>0</is_required>
      <is_searchable>0</is_searchable>
      <is_search_range>0</is_search_range>
      <weight>12</weight>
      <is_active>1</is_active>
      <is_view>0</is_view>
      <text_length>255</text_length>
      <date_format>mm/dd/yy</date_format>
      <note_columns>60</note_columns>
      <note_rows>4</note_rows>
      <column_name>cease_date</column_name>
      <custom_group_name>Direct_Debit_Mandate</custom_group_name>
    </CustomField>
    <CustomField>
      <name>Suspend_Date</name>
      <label>Suspend Date</label>
      <data_type>Date</data_type>
      <html_type>Select Date</html_type>
      <is_required>0</is_required>
      <is_searchable>0</is_searchable>
      <is_search_range>0</is_search_range>
      <weight>13</weight>
      <is_active>1</is_active>
      <is_view>0</is_view>
      <text_length>255</text_length>
      <date_format>mm/dd/yy</date_format>
      <note_columns>60</note_columns>
      <note_rows>4</note_rows>
      <column_name>suspend_date</column_name>
      <custom_group_name>Direct_Debit_Mandate</custom_group_name>
    </CustomField>
	<CustomField>
      <name>Reason</name>
      <label>Reason</label>
      <data_type>String</data_type>
      <html_type>Select</html_type>
      <is_required>0</is_required>
      <is_searchable>0</is_searchable>
      <is_search_range>0</is_search_range>
      <weight>14</weight>
      <is_active>1</is_active>
      <is_view>0</is_view>
      <text_length>255</text_length>
      <note_columns>60</note_columns>
      <note_rows>4</note_rows>
      <column_name>reason</column_name>
      <option_group_name>cease_reason</option_group_name>
      <custom_group_name>Direct_Debit_Mandate</custom_group_name>
    </CustomField>
	<CustomField>
      <name>Collection_Day</name>
      <label>Collection Day</label>
      <data_type>String</data_type>
      <html_type>Select</html_type>
      <is_required>0</is_required>
      <is_searchable>0</is_searchable>
      <is_search_range>0</is_search_range>
      <weight>15</weight>
      <is_active>1</is_active>
      <is_view>0</is_view>
      <text_length>255</text_length>
      <note_columns>60</note_columns>
      <note_rows>4</note_rows>
      <column_name>collection_day</column_name>
      <option_group_name>collection_day</option_group_name>
      <custom_group_name>Direct_Debit_Mandate</custom_group_name>
    </CustomField>
	<CustomField>
      <name>Authorization_Date</name>
      <label>Authorization Date</label>
      <data_type>Date</data_type>
      <html_type>Select Date</html_type>
      <is_required>0</is_required>
      <is_searchable>0</is_searchable>
      <is_search_range>0</is_search_range>
      <weight>16</weight>
      <is_active>1</is_active>
      <is_view>0</is_view>
      <text_length>255</text_length>
      <date_format>mm/dd/yy</date_format>
      <note_columns>60</note_columns>
      <note_rows>4</note_rows>
      <column_name>authorization_date</column_name>
      <custom_group_name>Direct_Debit_Mandate</custom_group_name>
    </CustomField>
    <CustomField>
      <name>Authorization_File</name>
      <label>Authorization File</label>
      <data_type>File</data_type>
      <html_type>File</html_type>
      <is_required>0</is_required>
      <is_searchable>0</is_searchable>
      <is_search_range>0</is_search_range>
      <weight>17</weight>
      <is_active>1</is_active>
      <is_view>0</is_view>
      <text_length>255</text_length>
      <note_columns>60</note_columns>
      <note_rows>4</note_rows>
      <column_name>authorization_file</column_name>
      <custom_group_name>Direct_Debit_Mandate</custom_group_name>
    </CustomField>
    <CustomField>
      <name>Default_Mandate_Id</name>
      <label>Default?</label>
      <data_type>String</data_type>
      <html_type>CheckBox</html_type>
      <is_required>0</is_required>
      <is_searchable>0</is_searchable>
      <is_search_range>0</is_search_range>
      <weight>18</weight>
      <is_active>1</is_active>
      <is_view>0</is_view>
      <text_length>255</text_length>
      <note_columns>60</note_columns>
      <note_rows>4</note_rows>
      <column_name>is_default</column_name>
      <help_pre>Mandate to be used to create member dues for auto-renew membership types.</help_pre>
      <option_group_name>isdefaultmandateid_20110531172050</option_group_name>
      <custom_group_name>Direct_Debit_Mandate</custom_group_name>
    </CustomField>
  </CustomFields>
  <OptionGroups>
  	<OptionGroup>
        <name>cease_reason</name>
        <label>Reason</label>
        <is_active>1</is_active>
    </OptionGroup>
    <OptionGroup>
        <name>addedtodirectdebitbatch_20101222111245</name>
        <label>Added to DD Batch?</label>
        <is_active>1</is_active>
    </OptionGroup>  
    <OptionGroup>
        <name>isdefaultmandateid_20110531172050</name>
        <label>Default Mandate?</label>
        <is_active>1</is_active>
    </OptionGroup>
  	<OptionGroup>
        <name>collection_day</name>
        <label>Collection Day</label>
        <is_active>1</is_active>
    </OptionGroup>
  </OptionGroups>
  <OptionValues>
    <OptionValue>
		  <label>Yes</label>
		  <value>1</value>
		  <is_default>0</is_default>
		  <weight>1</weight>
		  <is_optgroup>0</is_optgroup>
		  <is_reserved>0</is_reserved>
		  <is_active>1</is_active>
		  <option_group_name>isdefaultmandateid_20110531172050</option_group_name>
		</OptionValue>
	  <OptionValue>
		  <label>Account closed</label>
		  <value>12</value>
		  <name>Account_closed</name>
		  <is_default>0</is_default>
		  <weight>12</weight>
		  <is_optgroup>0</is_optgroup>
		  <is_reserved>0</is_reserved>
		  <is_active>1</is_active>
		  <option_group_name>cease_reason</option_group_name>
		</OptionValue>
		<OptionValue>
		  <label>Account transferred</label>
		  <value>4</value>
		  <name>Account_transferred</name>
		  <is_default>0</is_default>
		  <weight>4</weight>
		  <is_optgroup>0</is_optgroup>
		  <is_reserved>0</is_reserved>
		  <is_active>1</is_active>
		  <option_group_name>cease_reason</option_group_name>
		</OptionValue>
		<OptionValue>
		  <label>Account transferred to a different branch of Bank or Building Society</label>
		  <value>16</value>
		  <name>Account_transferred_to_a_differ</name>
		  <is_default>0</is_default>
		  <weight>16</weight>
		  <is_optgroup>0</is_optgroup>
		  <is_reserved>0</is_reserved>
		  <is_active>1</is_active>
		  <option_group_name>cease_reason</option_group_name>
		</OptionValue>
		<OptionValue>
		  <label>Account transferred to a new Bank or Building Society</label>
		  <value>15</value>
		  <name>Account_transferred_to_a_new_Ba</name>
		  <is_default>0</is_default>
		  <weight>15</weight>
		  <is_optgroup>0</is_optgroup>
		  <is_reserved>0</is_reserved>
		  <is_active>1</is_active>
		  <option_group_name>cease_reason</option_group_name>
		</OptionValue>
		<OptionValue>
		  <label>Advance Notice disputed</label>
		  <value>5</value>
		  <name>Advance_Notice_disputed</name>
		  <is_default>0</is_default>
		  <weight>5</weight>
		  <is_optgroup>0</is_optgroup>
		  <is_reserved>0</is_reserved>
		  <is_active>1</is_active>
		  <option_group_name>cease_reason</option_group_name>
		</OptionValue>
		<OptionValue>
		  <label>Amount Differs</label>
		  <value>8</value>
		  <name>Amount_Differs</name>
		  <is_default>0</is_default>
		  <weight>8</weight>
		  <is_optgroup>0</is_optgroup>
		  <is_reserved>0</is_reserved>
		  <is_active>1</is_active>
		  <option_group_name>cease_reason</option_group_name>
		</OptionValue>
		<OptionValue>
		  <label>Amount not yet due</label>
		  <value>9</value>
		  <name>Amount_not_yet_due</name>
		  <is_default>0</is_default>
		  <weight>9</weight>
		  <is_optgroup>0</is_optgroup>
		  <is_reserved>0</is_reserved>
		  <is_active>1</is_active>
		  <option_group_name>cease_reason</option_group_name>
		</OptionValue>
		<OptionValue>
		  <label>Instruction amended</label>
		  <value>17</value>
		  <name>Instruction_amended</name>
		  <is_default>0</is_default>
		  <weight>17</weight>
		  <is_optgroup>0</is_optgroup>
		  <is_reserved>0</is_reserved>
		  <is_active>1</is_active>
		  <option_group_name>cease_reason</option_group_name>
		</OptionValue>
		<OptionValue>
		  <label>Instruction cancelled</label>
		  <value>2</value>
		  <name>Instruction_cancelled</name>
		  <is_default>0</is_default>
		  <weight>2</weight>
		  <is_optgroup>0</is_optgroup>
		  <is_reserved>0</is_reserved>
		  <is_active>1</is_active>
		  <option_group_name>cease_reason</option_group_name>
		</OptionValue>
		<OptionValue>
		  <label>Instruction cancelled - Refer to Payer</label>
		  <value>13</value>
		  <name>Instruction_cancelled__Refer_to</name>
		  <is_default>0</is_default>
		  <weight>13</weight>
		  <is_optgroup>0</is_optgroup>
		  <is_reserved>0</is_reserved>
		  <is_active>1</is_active>
		  <option_group_name>cease_reason</option_group_name>
		</OptionValue>
		<OptionValue>
		  <label>Instruction cancelled by payer</label>
		  <value>14</value>
		  <name>Instruction_cancelled_by_payer</name>
		  <is_default>0</is_default>
		  <weight>14</weight>
		  <is_optgroup>0</is_optgroup>
		  <is_reserved>0</is_reserved>
		  <is_active>1</is_active>
		  <option_group_name>cease_reason</option_group_name>
		</OptionValue>
		<OptionValue>
		  <label>Instruction re-instated</label>
		  <value>18</value>
		  <name>Instruction_re_instated</name>
		  <is_default>0</is_default>
		  <weight>18</weight>
		  <is_optgroup>0</is_optgroup>
		  <is_reserved>0</is_reserved>
		  <is_active>1</is_active>
		  <option_group_name>cease_reason</option_group_name>
		</OptionValue>
		<OptionValue>
		  <label>No Account (or wrong account type)</label>
		  <value>6</value>
		  <name>No_Account__or_wrong_account_ty</name>
		  <is_default>0</is_default>
		  <weight>6</weight>
		  <is_optgroup>0</is_optgroup>
		  <is_reserved>0</is_reserved>
		  <is_active>1</is_active>
		  <option_group_name>cease_reason</option_group_name>
		</OptionValue>
		<OptionValue>
		  <label>No Instruction</label>
		  <value>7</value>
		  <name>No_Instruction</name>
		  <is_default>0</is_default>
		  <weight>7</weight>
		  <is_optgroup>0</is_optgroup>
		  <is_reserved>0</is_reserved>
		  <is_active>1</is_active>
		  <option_group_name>cease_reason</option_group_name>
		</OptionValue>
		<OptionValue>
		  <label>Originator differs</label>
		  <value>11</value>
		  <name>Originator_differs</name>
		  <is_default>0</is_default>
		  <weight>11</weight>
		  <is_optgroup>0</is_optgroup>
		  <is_reserved>0</is_reserved>
		  <is_active>1</is_active>
		  <option_group_name>cease_reason</option_group_name>
		</OptionValue>
		<OptionValue>
		  <label>Payer deceased</label>
		  <value>3</value>
		  <name>Payer_deceased</name>
		  <is_default>0</is_default>
		  <weight>3</weight>
		  <is_optgroup>0</is_optgroup>
		  <is_reserved>0</is_reserved>
		  <is_active>1</is_active>
		  <option_group_name>cease_reason</option_group_name>
		</OptionValue>
		<OptionValue>
		  <label>Presentation overdue</label>
		  <value>10</value>
		  <name>Presentation_overdue</name>
		  <is_default>0</is_default>
		  <weight>10</weight>
		  <is_optgroup>0</is_optgroup>
		  <is_reserved>0</is_reserved>
		  <is_active>1</is_active>
		  <option_group_name>cease_reason</option_group_name>
		</OptionValue>
		<OptionValue>
		  <label>Refer to Payer</label>
		  <value>1</value>
		  <name>Refer_to_Payer</name>
		  <is_default>0</is_default>
		  <weight>1</weight>
		  <is_optgroup>0</is_optgroup>
		  <is_reserved>0</is_reserved>
		  <is_active>1</is_active>
		  <option_group_name>cease_reason</option_group_name>
		</OptionValue>
		<OptionValue>
		  <label>10</label>
		  <value>10</value>
		  <name>10</name>
		  <is_default>0</is_default>
		  <weight>10</weight>
		  <is_optgroup>0</is_optgroup>
		  <is_reserved>0</is_reserved>
		  <is_active>1</is_active>
		  <option_group_name>collection_day</option_group_name>
		</OptionValue>
		<OptionValue>
		  <label>11</label>
		  <value>11</value>
		  <name>11</name>
		  <is_default>0</is_default>
		  <weight>11</weight>
		  <is_optgroup>0</is_optgroup>
		  <is_reserved>0</is_reserved>
		  <is_active>1</is_active>
		  <option_group_name>collection_day</option_group_name>
		</OptionValue>
		<OptionValue>
		  <label>12</label>
		  <value>12</value>
		  <name>12</name>
		  <is_default>0</is_default>
		  <weight>12</weight>
		  <is_optgroup>0</is_optgroup>
		  <is_reserved>0</is_reserved>
		  <is_active>1</is_active>
		  <option_group_name>collection_day</option_group_name>
		</OptionValue>
		<OptionValue>
		  <label>13</label>
		  <value>13</value>
		  <name>13</name>
		  <is_default>0</is_default>
		  <weight>13</weight>
		  <is_optgroup>0</is_optgroup>
		  <is_reserved>0</is_reserved>
		  <is_active>1</is_active>
		  <option_group_name>collection_day</option_group_name>
		</OptionValue>
		<OptionValue>
		  <label>14</label>
		  <value>14</value>
		  <name>14</name>
		  <is_default>0</is_default>
		  <weight>14</weight>
		  <is_optgroup>0</is_optgroup>
		  <is_reserved>0</is_reserved>
		  <is_active>1</is_active>
		  <option_group_name>collection_day</option_group_name>
		</OptionValue>
		<OptionValue>
		  <label>15</label>
		  <value>15</value>
		  <name>15</name>
		  <is_default>0</is_default>
		  <weight>15</weight>
		  <is_optgroup>0</is_optgroup>
		  <is_reserved>0</is_reserved>
		  <is_active>1</is_active>
		  <option_group_name>collection_day</option_group_name>
		</OptionValue>
		<OptionValue>
		  <label>16</label>
		  <value>16</value>
		  <name>16</name>
		  <is_default>0</is_default>
		  <weight>16</weight>
		  <is_optgroup>0</is_optgroup>
		  <is_reserved>0</is_reserved>
		  <is_active>1</is_active>
		  <option_group_name>collection_day</option_group_name>
		</OptionValue>
		<OptionValue>
		  <label>6</label>
		  <value>6</value>
		  <name>1679091c5a880faf6fb5e6087eb1b2d</name>
		  <is_default>0</is_default>
		  <weight>6</weight>
		  <is_optgroup>0</is_optgroup>
		  <is_reserved>0</is_reserved>
		  <is_active>1</is_active>
		  <option_group_name>collection_day</option_group_name>
		</OptionValue>
		<OptionValue>
		  <label>17</label>
		  <value>17</value>
		  <name>17</name>
		  <is_default>0</is_default>
		  <weight>17</weight>
		  <is_optgroup>0</is_optgroup>
		  <is_reserved>0</is_reserved>
		  <is_active>1</is_active>
		  <option_group_name>collection_day</option_group_name>
		</OptionValue>
		<OptionValue>
		  <label>18</label>
		  <value>18</value>
		  <name>18</name>
		  <is_default>0</is_default>
		  <weight>18</weight>
		  <is_optgroup>0</is_optgroup>
		  <is_reserved>0</is_reserved>
		  <is_active>1</is_active>
		  <option_group_name>collection_day</option_group_name>
		</OptionValue>
		<OptionValue>
		  <label>19</label>
		  <value>19</value>
		  <name>19</name>
		  <is_default>0</is_default>
		  <weight>19</weight>
		  <is_optgroup>0</is_optgroup>
		  <is_reserved>0</is_reserved>
		  <is_active>1</is_active>
		  <option_group_name>collection_day</option_group_name>
		</OptionValue>
		<OptionValue>
		  <label>20</label>
		  <value>20</value>
		  <name>20</name>
		  <is_default>0</is_default>
		  <weight>20</weight>
		  <is_optgroup>0</is_optgroup>
		  <is_reserved>0</is_reserved>
		  <is_active>1</is_active>
		  <option_group_name>collection_day</option_group_name>
		</OptionValue>
		<OptionValue>
		  <label>21</label>
		  <value>21</value>
		  <name>21</name>
		  <is_default>0</is_default>
		  <weight>21</weight>
		  <is_optgroup>0</is_optgroup>
		  <is_reserved>0</is_reserved>
		  <is_active>1</is_active>
		  <option_group_name>collection_day</option_group_name>
		</OptionValue>
		<OptionValue>
		  <label>22</label>
		  <value>22</value>
		  <name>22</name>
		  <is_default>0</is_default>
		  <weight>22</weight>
		  <is_optgroup>0</is_optgroup>
		  <is_reserved>0</is_reserved>
		  <is_active>1</is_active>
		  <option_group_name>collection_day</option_group_name>
		</OptionValue>
		<OptionValue>
		  <label>23</label>
		  <value>23</value>
		  <name>23</name>
		  <is_default>0</is_default>
		  <weight>23</weight>
		  <is_optgroup>0</is_optgroup>
		  <is_reserved>0</is_reserved>
		  <is_active>1</is_active>
		  <option_group_name>collection_day</option_group_name>
		</OptionValue>
		<OptionValue>
		  <label>24</label>
		  <value>24</value>
		  <name>24</name>
		  <is_default>0</is_default>
		  <weight>24</weight>
		  <is_optgroup>0</is_optgroup>
		  <is_reserved>0</is_reserved>
		  <is_active>1</is_active>
		  <option_group_name>collection_day</option_group_name>
		</OptionValue>
		<OptionValue>
		  <label>25</label>
		  <value>25</value>
		  <name>25</name>
		  <is_default>0</is_default>
		  <weight>25</weight>
		  <is_optgroup>0</is_optgroup>
		  <is_reserved>0</is_reserved>
		  <is_active>1</is_active>
		  <option_group_name>collection_day</option_group_name>
		</OptionValue>
		<OptionValue>
		  <label>26</label>
		  <value>26</value>
		  <name>26</name>
		  <is_default>0</is_default>
		  <weight>26</weight>
		  <is_optgroup>0</is_optgroup>
		  <is_reserved>0</is_reserved>
		  <is_active>1</is_active>
		  <option_group_name>collection_day</option_group_name>
		</OptionValue>
		<OptionValue>
		  <label>27</label>
		  <value>27</value>
		  <name>27</name>
		  <is_default>0</is_default>
		  <weight>27</weight>
		  <is_optgroup>0</is_optgroup>
		  <is_reserved>0</is_reserved>
		  <is_active>1</is_active>
		  <option_group_name>collection_day</option_group_name>
		</OptionValue>
		<OptionValue>
		  <label>28</label>
		  <value>28</value>
		  <name>28</name>
		  <is_default>0</is_default>
		  <weight>28</weight>
		  <is_optgroup>0</is_optgroup>
		  <is_reserved>0</is_reserved>
		  <is_active>1</is_active>
		  <option_group_name>collection_day</option_group_name>
		</OptionValue>
		<OptionValue>
		  <label>29</label>
		  <value>29</value>
		  <name>29</name>
		  <is_default>0</is_default>
		  <weight>29</weight>
		  <is_optgroup>0</is_optgroup>
		  <is_reserved>0</is_reserved>
		  <is_active>1</is_active>
		  <option_group_name>collection_day</option_group_name>
		</OptionValue>
		<OptionValue>
		  <label>30</label>
		  <value>30</value>
		  <name>30</name>
		  <is_default>0</is_default>
		  <weight>30</weight>
		  <is_optgroup>0</is_optgroup>
		  <is_reserved>0</is_reserved>
		  <is_active>1</is_active>
		  <option_group_name>collection_day</option_group_name>
		</OptionValue>
		<OptionValue>
		  <label>9</label>
		  <value>9</value>
		  <name>45c48cce2e2d7fbdea1afc51c7c6ad2</name>
		  <is_default>0</is_default>
		  <weight>9</weight>
		  <is_optgroup>0</is_optgroup>
		  <is_reserved>0</is_reserved>
		  <is_active>1</is_active>
		  <option_group_name>collection_day</option_group_name>
		</OptionValue>
		<OptionValue>
		  <label>7</label>
		  <value>7</value>
		  <name>8f14e45fceea167a5a36dedd4bea254</name>
		  <is_default>0</is_default>
		  <weight>7</weight>
		  <is_optgroup>0</is_optgroup>
		  <is_reserved>0</is_reserved>
		  <is_active>1</is_active>
		  <option_group_name>collection_day</option_group_name>
		</OptionValue>
		<OptionValue>
		  <label>4</label>
		  <value>4</value>
		  <name>a87ff679a2f3e71d9181a67b7542122</name>
		  <is_default>0</is_default>
		  <weight>4</weight>
		  <is_optgroup>0</is_optgroup>
		  <is_reserved>0</is_reserved>
		  <is_active>1</is_active>
		  <option_group_name>collection_day</option_group_name>
		</OptionValue>
		<OptionValue>
		  <label>1</label>
		  <value>1</value>
		  <name>c4ca4238a0b923820dcc509a6f75849</name>
		  <is_default>0</is_default>
		  <weight>1</weight>
		  <is_optgroup>0</is_optgroup>
		  <is_reserved>0</is_reserved>
		  <is_active>1</is_active>
		  <option_group_name>collection_day</option_group_name>
		</OptionValue>
		<OptionValue>
		  <label>2</label>
		  <value>2</value>
		  <name>c81e728d9d4c2f636f067f89cc14862</name>
		  <is_default>0</is_default>
		  <weight>2</weight>
		  <is_optgroup>0</is_optgroup>
		  <is_reserved>0</is_reserved>
		  <is_active>1</is_active>
		  <option_group_name>collection_day</option_group_name>
		</OptionValue>
		<OptionValue>
		  <label>8</label>
		  <value>8</value>
		  <name>c9f0f895fb98ab9159f51fd0297e236</name>
		  <is_default>0</is_default>
		  <weight>8</weight>
		  <is_optgroup>0</is_optgroup>
		  <is_reserved>0</is_reserved>
		  <is_active>1</is_active>
		  <option_group_name>collection_day</option_group_name>
		</OptionValue>
		<OptionValue>
		  <label>5</label>
		  <value>5</value>
		  <name>e4da3b7fbbce2345d7772b0674a318d</name>
		  <is_default>0</is_default>
		  <weight>5</weight>
		  <is_optgroup>0</is_optgroup>
		  <is_reserved>0</is_reserved>
		  <is_active>1</is_active>
		  <option_group_name>collection_day</option_group_name>
		</OptionValue>
		<OptionValue>
		  <label>3</label>
		  <value>3</value>
		  <name>eccbc87e4b5ce2fe28308fd9f2a7baf</name>
		  <is_default>0</is_default>
		  <weight>3</weight>
		  <is_optgroup>0</is_optgroup>
		  <is_reserved>0</is_reserved>
		  <is_active>1</is_active>
		  <option_group_name>collection_day</option_group_name>
		</OptionValue>
	</OptionValues>
</CustomData>